cinemaxplus/__init__.py
cinemaxplus/version.py
cinemaxplus-1.0.0.dist-info/METADATA
cinemaxplus-1.0.0.dist-info/WHEEL
cinemaxplus-1.0.0.dist-info/top_level.txt
cinemaxplus-1.0.0.dist-info/zip-safe
cinemaxplus-1.0.0.dist-info/RECORD
